testix/DSL.py
testix/__init__.py
testix/argumentexpectations.py
testix/call_character.py
testix/call_formatter.py
testix/call_modifiers/__init__.py
testix/call_modifiers/asynchronous.py
testix/call_modifiers/awaitable.py
testix/call_modifiers/base.py
testix/call_modifiers/synchronous.py
testix/call_modifiers/trivial.py
testix/expectationmaker.py
testix/expectations/__init__.py
testix/expectations/call.py
testix/failhooks.py
testix/fake.py
testix/fake_privacy_violator.py
testix/fakefile.py
testix/fakeobject.py
testix/frequentlyused.py
testix/hook.py
testix/loop_breaker.py
testix/patch_module.py
testix/saveargument.py
testix/scenario.py
testix/scenario_mocks.py
testix/testixexception.py
testix-12.1.0.dist-info/LICENSE
testix-12.1.0.dist-info/METADATA
testix-12.1.0.dist-info/WHEEL
testix-12.1.0.dist-info/RECORD
