Metadata-Version: 2.3
Name: testix
Version: 12.1.0
Summary: Mocking framework Python with *exact* Scenarios
License: MIT License
Keywords: mock,TDD,testix,tests,Test Driven Development
Author: Yoav Kleinberger
Author-email: haarcuba@gmail.com
Maintainer: Yoav Kleinberger
Maintainer-email: haarcuba@gmail.com
Requires-Python: >=3.8
Classifier: Intended Audience :: Developers
Classifier: License :: OSI Approved :: MIT License
Classifier: License :: Other/Proprietary License
Classifier: Operating System :: OS Independent
Classifier: Programming Language :: Python
Classifier: Programming Language :: Python :: 3
Classifier: Programming Language :: Python :: 3.8
Classifier: Programming Language :: Python :: 3.9
Classifier: Programming Language :: Python :: 3.10
Classifier: Programming Language :: Python :: 3.11
Classifier: Programming Language :: Python :: 3.12
Classifier: Programming Language :: Python :: 3.13
Classifier: Topic :: Software Development :: Testing
Requires-Dist: pytest (>=8.1.1,<9.0.0)
Project-URL: Documentation, https://testix.readthedocs.io/en/latest
Project-URL: Homepage, https://testix.readthedocs.io/en/latest
Project-URL: Repository, https://github.com/haarcuba/testix.git
